{
  "id": "rob-training-day",
  "rob": true,
  "title": "Training Day",
  "starring": "Jenna Ortega, Jesse Eisenberg",
  "poster": "/assets/img/posters/robs/training-day-rob.webp",
  "coherence": 8,
  "entertainment": 7,
  "originality": 7,

  "podcastDate": "2026-03-07",
  "podcasted_at": "2026-03-07",
  "summary": "Recent graduate Ava signs up to attend an open recruitment day at a Californian big-tech firm and finds herself in control of a terminal connected directly to their supercomputer. Harnessing its awesome power, she creates code that can change any digitally-stored number. But how will she wield this power, and just how long can she stay in control?",
  "link": "#",
  "linkType": "podcast"


}
